Metadata-Version: 1.0
Name: funniest420
Version: 0.8
Summary: The funniest joke in the world
Home-page: http://github.com/storborg/funniest
Author: Flying Circus
Author-email: flyingcircus@example.com
License: MIT
Platform: UNKNOWN
